openapi_navigator/__init__.py
openapi_navigator/server.py
openapi_navigator/spec_manager.py
openapi_navigator-0.6.0.dist-info/METADATA
openapi_navigator-0.6.0.dist-info/WHEEL
openapi_navigator-0.6.0.dist-info/entry_points.txt
openapi_navigator-0.6.0.dist-info/RECORD
