Metadata-Version: 2.4
Name: openapi-navigator
Version: 0.6.0
Summary: OpenAPI Navigator - MCP server for navigating OpenAPI specifications
Author-email: Mike Garuccio <mike.garuccio@expedient.com>
Requires-Python: >=3.10
Requires-Dist: fastmcp>=2.11.3
Requires-Dist: fuzzywuzzy>=0.18.0
Requires-Dist: jsonschema>=4.20.0
Requires-Dist: pydantic-settings>=2.10.1
Requires-Dist: python-levenshtein>=0.23.0
Requires-Dist: pyyaml>=6.0.1
Requires-Dist: requests>=2.31.0
